dcm/__init__.py
dcm/models.py
dcm/parser.py
dcm/spec.py
docker_compose_model-0.0.2.dist-info/METADATA
docker_compose_model-0.0.2.dist-info/WHEEL
docker_compose_model-0.0.2.dist-info/licenses/LICENSE
docker_compose_model-0.0.2.dist-info/RECORD
